agentmem/__init__.py
agentmem/base.py
agentmem/concurrency.py
agentmem/episodic/__init__.py
agentmem/episodic/episodic_memory.py
agentmem/logging/__init__.py
agentmem/logging/logger.py
agentmem/logging/memory_usage.py
agentmem/logging/metrics.py
agentmem/procedural/__init__.py
agentmem/procedural/procedural_memory.py
agentmem/semantic/__init__.py
agentmem/semantic/semantic_memory.py
agentmem/storage/__init__.py
agentmem/storage/file_storage.py
agentmem/storage/vector_storage.py
agentmem-0.3.0.dist-info/licenses/LICENSE
tests/__init__.py
tests/test_concurrency.py
tests/test_episodic_memory.py
tests/test_integration.py
tests/test_lock_monitoring.py
tests/test_performance.py
tests/test_procedural_memory.py
tests/test_semantic_memory.py
agentmem-0.3.0.dist-info/METADATA
agentmem-0.3.0.dist-info/WHEEL
agentmem-0.3.0.dist-info/top_level.txt
agentmem-0.3.0.dist-info/RECORD
