Metadata-Version: 2.4
Name: agentmem
Version: 0.3.0
Summary: A Python package for managing AI agent memory systems with persistence and vector search
Home-page: https://github.com/maxgoff/AgentMem
Author: Max Goff
Author-email: max.goff@gmail.com
Project-URL: Documentation, https://github.com/maxgoff/AgentMem
Project-URL: Bug Reports, https://github.com/maxgoff/AgentMem
Project-URL: Source Code, https://github.com/maxgoff/AgentMem
Keywords: ai,memory,agent,semantic,episodic,procedural,persistence,vector search
Classifier: Development Status :: 4 - Beta
Classifier: Intended Audience :: Developers
Classifier: Intended Audience :: Science/Research
Classifier: License :: OSI Approved :: MIT License
Classifier: Programming Language :: Python :: 3
Classifier: Programming Language :: Python :: 3.8
Classifier: Programming Language :: Python :: 3.9
Classifier: Programming Language :: Python :: 3.10
Classifier: Programming Language :: Python :: 3.11
Classifier: Topic :: Scientific/Engineering :: Artificial Intelligence
Classifier: Operating System :: OS Independent
Requires-Python: >=3.8
License-File: LICENSE
Requires-Dist: pydantic>=2.0.0
Requires-Dist: numpy>=1.20.0
Requires-Dist: sentence-transformers>=2.2.2
Requires-Dist: chromadb>=0.4.0
Requires-Dist: joblib>=1.2.0
Provides-Extra: dev
Requires-Dist: pytest>=7.0.0; extra == "dev"
Requires-Dist: black>=23.0.0; extra == "dev"
Requires-Dist: isort>=5.0.0; extra == "dev"
Requires-Dist: flake8>=6.0.0; extra == "dev"
Provides-Extra: vector
Requires-Dist: sentence-transformers>=2.2.2; extra == "vector"
Requires-Dist: chromadb>=0.4.0; extra == "vector"
Dynamic: author
Dynamic: author-email
Dynamic: classifier
Dynamic: description
Dynamic: description-content-type
Dynamic: home-page
Dynamic: keywords
Dynamic: license-file
Dynamic: project-url
Dynamic: provides-extra
Dynamic: requires-dist
Dynamic: requires-python
Dynamic: summary
